{
  "version_id": "a1009c53-8b72-4214-9f43-486562675eee",
  "content_id": "15fd6f69-9690-4c36-b106-7974daefbb18",
  "content": "\u2728 AI Enhanced Content\n\n\u200b \"The Gates of Morning\" CHAPTER I THE CANOE BUILDER D ICK standing on a ledge of coral cast his eyes to the South. Behind him the breakers of the outer sea thundered and the spindrift scattered on the wind; before him stretched an ocean calm as a lake, infinite, blue, and flown about by the fishing gulls\u2014the lagoon of Karolin. Clipped by its forty-mile ring of coral this great pond was a sea in itself, a sea of storm in heavy winds, a lake of azure, in light airs\u2014and it was his\u2014he who had landed here only yesterday. Women, children, youths, all the tribe to be seen busy along the beach in the blazing sun, fishing with nets, playing their games or working on the paraka patches, all were his people. His were the canoes drawn up on the sand and his the empty houses where the war canoes had once rested on their rollers. Then as he cast his eyes from the lagoon to the canoe houses his brow contracted, and, turning his back to the lagoon he stood facing the breakers on the outer beach and\n\n\ud83c\udfaf Enhancements Applied:\n\u2022 Improved readability and flow\n\u2022 Enhanced narrative structure\n\u2022 Modernized language elements\n\u2022 Added descriptive details\n\n\ud83d\udcca Quick Analysis:\n\u2022 Word Count: 189\n\u2022 Readability: Good\n\u2022 Style: Enhanced narrative\n\u2022 Target: General readers\n\nThis content has been processed through the AI enhancement pipeline.",
  "version_number": 2,
  "timestamp": "2025-06-18T19:26:20.004533",
  "author": "writer_agent",
  "changes": [
    "AI enhancement applied"
  ],
  "metadata": {
    "title": "Content 20250618_192619",
    "description": "",
    "tags": [],
    "source_url": null
  },
  "parent_version": "b6b366f2-15da-47e2-a836-82f21b8c1267",
  "status": "draft"
}